ms2deepscore/MS2DeepScore.py
ms2deepscore/MS2DeepScoreEvaluated.py
ms2deepscore/MetadataFeatureGenerator.py
ms2deepscore/SettingsMS2Deepscore.py
ms2deepscore/__init__.py
ms2deepscore/__version__.py
ms2deepscore/tensorize_spectra.py
ms2deepscore/utils.py
ms2deepscore/vector_operations.py
ms2deepscore/benchmarking/CalculateScoresBetweenAllIonmodes.py
ms2deepscore/benchmarking/__init__.py
ms2deepscore/benchmarking/plot_average_per_bin.py
ms2deepscore/benchmarking/plot_heatmaps.py
ms2deepscore/benchmarking/plot_loss_per_bin.py
ms2deepscore/models/EmbeddingEvaluatorModel.py
ms2deepscore/models/LinearEmbeddingEvaluation.py
ms2deepscore/models/SiameseSpectralModel.py
ms2deepscore/models/__init__.py
ms2deepscore/models/__model_format__.py
ms2deepscore/models/helper_functions.py
ms2deepscore/models/io_utils.py
ms2deepscore/models/legacy_model_converter.py
ms2deepscore/models/load_model.py
ms2deepscore/models/loss_functions.py
ms2deepscore/train_new_model/__init__.py
ms2deepscore/train_new_model/data_generators.py
ms2deepscore/train_new_model/inchikey_pair_selection.py
ms2deepscore/train_new_model/split_positive_and_negative_mode.py
ms2deepscore/train_new_model/train_ms2deepscore.py
ms2deepscore/train_new_model/validation_and_test_split.py
ms2deepscore/validation_loss_calculation/PredictionsAndTanimotoScores.py
ms2deepscore/validation_loss_calculation/ValidationLossCalculator.py
ms2deepscore/validation_loss_calculation/__init__.py
ms2deepscore/validation_loss_calculation/calculate_scores_for_validation.py
ms2deepscore/wrapper_functions/__init__.py
ms2deepscore/wrapper_functions/plotting_wrapper_functions.py
ms2deepscore/wrapper_functions/training_wrapper_functions.py
ms2deepscore-2.6.0.dist-info/licenses/LICENSE
tests/__init__.py
tests/create_test_spectra.py
tests/test_CalculateScoresBetweenAllIonmodes.py
tests/test_MetadataFeatureGenerator.py
tests/test_PredictionsAndTanimotoScores.py
tests/test_SettingsMS2deepscore.py
tests/test_calculate_scores_for_validation.py
tests/test_converter_legacy.py
ms2deepscore-2.6.0.dist-info/METADATA
ms2deepscore-2.6.0.dist-info/WHEEL
ms2deepscore-2.6.0.dist-info/top_level.txt
ms2deepscore-2.6.0.dist-info/RECORD
