Metadata-Version: 2.4
Name: ms2deepscore
Version: 2.6.0
Summary: Deep learning similarity measure for comparing MS/MS spectra.
Home-page: https://github.com/iomega/ms2deepscore
Author: Florian Huber (as part of the ms2deepscore developer team)
Author-email: florian.huber@hs-duesseldorf.de
License: Apache Software License 2.0
Requires-Python: >=3.10
License-File: LICENSE
Requires-Dist: matchms>=0.19.0
Requires-Dist: numba
Requires-Dist: numpy>=2.0
Requires-Dist: pandas
Requires-Dist: scikit-learn
Requires-Dist: tensorboard
Requires-Dist: torch>=2.4
Requires-Dist: tqdm
Requires-Dist: matplotlib>=3.8.3
Provides-Extra: train
Requires-Dist: rdkit; extra == "train"
Provides-Extra: dev
Requires-Dist: bump2version; extra == "dev"
Requires-Dist: isort>=4.2.5; extra == "dev"
Requires-Dist: ruff; extra == "dev"
Requires-Dist: pytest; extra == "dev"
Requires-Dist: pytest-cov; extra == "dev"
Requires-Dist: sphinx!=3.2.0,<4.0.0,>=3.0.0; extra == "dev"
Requires-Dist: sphinx_rtd_theme; extra == "dev"
Requires-Dist: sphinxcontrib-apidoc; extra == "dev"
Requires-Dist: yapf; extra == "dev"
Dynamic: author
Dynamic: author-email
Dynamic: description
Dynamic: description-content-type
Dynamic: home-page
Dynamic: license
Dynamic: license-file
Dynamic: provides-extra
Dynamic: requires-dist
Dynamic: requires-python
Dynamic: summary
